{
  "_fv": 24,
  "_type": "rangeditem",
  "definition": {
    "renderType": 0,
    "texture": "icewingfrostbreath",
    "customModelName": "Normal",
    "name": "Icewing Frostbreath",
    "specialInfo": [],
    "creativeTab": {
      "value": "CUSTOM:WofWeapons"
    },
    "stackSize": 1,
    "ammoItem": {
      "value": ""
    },
    "shootConstantly": false,
    "usageCount": 100000,
    "actionSound": {
      "value": "entity.arrow.shoot"
    },
    "hasGlow": false,
    "animation": "drink",
    "enableMeleeDamage": false,
    "damageVsEntity": 7.0,
    "onRangedItemUsed": {
      "name": "IcewingFrostbreathRangedItemUsed"
    },
    "bulletPower": 1.0,
    "bulletDamage": 7.0,
    "bulletKnockback": 5,
    "bulletParticles": true,
    "bulletIgnitesFire": false,
    "bulletItemTexture": {
      "value": "Items.SNOWBALL"
    },
    "bulletModel": "Default",
    "customBulletModelTexture": "",
    "onBulletHitsPlayer": {
      "name": "IcewingFrostbreathProjectileHitsPlayer"
    },
    "onBulletHitsEntity": {
      "name": "IcewingFrostbreathProjectileHitsPlayer"
    }
  }
}